symmetrypy/__init__.py
symmetrypy/src/__ini__.py
symmetrypy/src/connection.py
symmetrypy/src/rpc.py
symmetrypy/src/values.py
symmetrypy-0.1.3.dist-info/METADATA
symmetrypy-0.1.3.dist-info/WHEEL
symmetrypy-0.1.3.dist-info/top_level.txt
symmetrypy-0.1.3.dist-info/RECORD
