Metadata-Version: 2.1
Name: symmetrypy
Version: 0.1.3
Summary: Solana RPC API for symmetry 
Home-page: UNKNOWN
License: UNKNOWN
Keywords: symmetry blockchain solana
Platform: UNKNOWN
Classifier: Development Status :: 1 - Planning
Requires-Python: >=3.8, <4
